llm_fal.py
llm_fal-0.1.0.dist-info/METADATA
llm_fal-0.1.0.dist-info/WHEEL
llm_fal-0.1.0.dist-info/entry_points.txt
llm_fal-0.1.0.dist-info/licenses/LICENSE
llm_fal-0.1.0.dist-info/RECORD
