Metadata-Version: 2.4
Name: llm-fal
Version: 0.1.0
Summary: LLM CLI plugin for fal.ai generative AI models and services
Project-URL: Homepage, https://github.com/nicobailon/llm-fal
Project-URL: Issues, https://github.com/nicobailon/llm-fal/issues
Author: LLM CLI Contributors
License: MIT
License-File: LICENSE
Classifier: License :: OSI Approved :: MIT License
Classifier: Programming Language :: Python :: 3
Classifier: Programming Language :: Python :: 3.8
Classifier: Programming Language :: Python :: 3.9
Classifier: Programming Language :: Python :: 3.10
Classifier: Programming Language :: Python :: 3.11
Classifier: Programming Language :: Python :: 3.12
Requires-Python: >=3.8
Requires-Dist: aiohttp<4.0.0,>=3.8.0
Requires-Dist: fal-client<1.0.0,>=0.2.0
Requires-Dist: llm<1.0.0,>=0.23
Provides-Extra: dev
Requires-Dist: black<24.0.0,>=23.0.0; extra == 'dev'
Requires-Dist: isort<6.0.0,>=5.0.0; extra == 'dev'
Requires-Dist: mypy<2.0.0,>=1.0.0; extra == 'dev'
Requires-Dist: ruff<1.0.0,>=0.0.0; extra == 'dev'
Provides-Extra: test
Requires-Dist: pytest-asyncio<1.0.0,>=0.18.0; extra == 'test'
Requires-Dist: pytest-cov<5.0.0,>=4.0.0; extra == 'test'
Requires-Dist: pytest-mock<4.0.0,>=3.10.0; extra == 'test'
Requires-Dist: pytest-vcr<2.0.0,>=1.0.0; extra == 'test'
Requires-Dist: pytest<8.0.0,>=7.0.0; extra == 'test'
